Workbook

Sheet Dashboard & Summary Overview
A1: BUSINESS PERFORMANCE DASHBOARD
A3: Financial & Inventory Health Summary (Real-Time)
A4: Metric KPI | B4: Value | C4: Source Reference Summary
A5: Total Value of Products Procured (Landed Cost) | B5: ='Purchase Order & Landed Cost'!Q7 -> 0 | C5: Total operational expenditure deployed for imports
A6: Total Sales Revenue Realized | B6: ='Sales Tracking & Revenue'!J7 -> 1080000 | C6: Gross sales receipts from product distributions
A7: Total Estimated Gross Profit | B7: ='Sales Tracking & Revenue'!L7 -> 345200 | C7: Cumulative profit before accounting operational deductions
A8: Total Capital Currently Tied in Warehouse Inventory | B8: ='Warehouse Inventory Management'!G7 -> 1286145 | C8: Current value of asset stock sitting in the warehouse
A9: Total Units Currently in Stock | B9: ='Warehouse Inventory Management'!E7 -> 17500 | C9: Sum total of items physically present across all SKUs

Sheet Landed costs 
A1: SHIPMENT LANDED COST & PROFIT MARGIN TRACKER
A3: PO Number | B3: Consignment Number | C3: LC/TT Number | D3: Date | E3: Product Name | F3: Product Code | G3: Purchase/U (FOB) | H3: CBM/U | I3: Sea Freight/U | J3: Customs Duty /U | K3: C&F Cost/U | L3: Local Transport/U | M3: Bank LC Fee & Insurance/U | N3: Labour/U | O3: Total Cost/U (Landed) | P3: QTY | Q3: Total Cost /Shipment | R3: Sale Price/U | S3: Total Sale /Shipment | T3: Approx Profit (Shipment) | U3: Profit/Pcs
A4: PO-2026-001 | B4: CN-9982 | C4: LC-77612 | D4: 2026-06-24 | E4: Dialyzer | F4: Mip001 | G4: 20 | I4: 7.23 | J4: 49.7 | K4: 2.38 | L4: 1 | M4: 1.4 | N4: 0.33 | O4: =SUM(G4, I4:N4) -> 82.04 | P4: 4500 | Q4: =O4*P4 -> 369180 | R4: 640 | S4: =R4*P4 -> 2880000 | T4: =S4-Q4 -> 2510820 | U4: =R4-O4 -> 557.96
A5: PO-2026-001 | B5: CN-9982 | C5: LC-77612 | D5: 2026-06-24 | E5: BTS | F5: Mip002 | G5: 5 | I5: 4.59 | J5: 38.77 | K5: 2.38 | L5: 1 | M5: 1.4 | N5: 0.33 | O5: =SUM(G5, I5:N5) -> 53.47 | P5: 4500 | Q5: =O5*P5 -> 240615 | R5: 215 | S5: =R5*P5 -> 967500 | T5: =S5-Q5 -> 726885 | U5: =R5-O5 -> 161.53
A6: PO-2026-001 | B6: CN-9982 | C6: LC-77612 | D6: 2026-06-24 | E6: A.V Fistula N | F6: Mip003 | G6: 3 | I6: 0.75 | J6: 2.71 | K6: 0.12 | L6: 0.06 | M6: 0.08 | N6: 0.02 | O6: =SUM(G6, I6:N6) -> 6.74 | P6: 35000 | Q6: =O6*P6 -> 235900 | R6: 54 | S6: =R6*P6 -> 1890000 | T6: =S6-Q6 -> 1654100 | U6: =R6-O6 -> 47.26
A7: Total Summary | Q7: =SUM(Q4:Q6) -> 845695 | S7: =SUM(S4:S6) -> 5737500 | T7: =SUM(T4:T6) -> 4891805

Sheet Purchase Order & Landed Cost
A1: PURCHASE ORDER & ACCURATE LANDED COST LOG
A3: PO Number | B3: Consignment No | C3: LC/TT Number | D3: Date | E3: Product Name | F3: Product Code | G3: Purchase/U (FOB) | H3: Sea Freight/U | I3: Customs Duty/U | J3: C&F Cost/U | K3: Local Transport/U | L3: Bank LC & Ins/U | M3: Labour/U | N3: Total Landed Cost/U | O3: QTY Ordered | P3: Total Cost/Shipment | Q3: Initial Sale Price/U
A4: PO-2026-001 | B4: CN-9982 | C4: LC-77612 | D4: 2026-06-24 | E4: Dialyzer | F4: Mip001 | G4: 393.6 | H4: 7.23 | I4: 49.7 | J4: 2.38 | K4: 1 | L4: 1.4 | M4: 0.33 | N4: =SUM(G4,H4:M4) -> 455.64 | O4: 4500 | P4: =N4*O4 -> 2050380 | Q4: 640
A5: PO-2026-001 | B5: CN-9982 | C5: LC-77612 | D5: 2026-06-24 | E5: Blood Tubing Set | F5: Mip002 | G5: 137.8 | H5: 4.59 | I5: 38.77 | J5: 2.38 | K5: 1 | L5: 1.4 | M5: 0.33 | N5: =SUM(G5,H5:M5) -> 186.27 | O5: 4500 | P5: =N5*O5 -> 838215 | Q5: 215
A6: PO-2026-001 | B6: CN-9982 | C6: LC-77612 | D6: 2026-06-24 | E6: A.V Fistula Needle | F6: Mip003 | G6: 33 | H6: 0.75 | I6: 2.71 | J6: 0.12 | K6: 0.06 | L6: 0.08 | M6: 0.02 | N6: =SUM(G6,H6:M6) -> 36.74 | O6: 35000 | P6: =N6*O6 -> 1285900 | Q6: 54
A7: Total Summary | O7: =SUM(O4:O6) -> 44000 | P7: =SUM(P4:P6) -> 4174495

Sheet Warehouse Inventory Management
A1: DYNAMIC WAREHOUSE INVENTORY CONTROL
A3: Product Code | B3: Product Name | C3: Total Received QTY | D3: Total Sold QTY | E3: Current Stock in Hand | F3: Unit Landed Cost | G3: Total Stock Asset Value
A4: Mip001 | B4: Dialyzer | C4: ='Purchase Order & Landed Cost'!O4 -> 4500 | D4: =SUMIF('Sales Tracking & Revenue'!E$4:E$10, A4, 'Sales Tracking & Revenue'!G$4:G$10) -> 3500 | E4: =C4-D4 -> 1000 | F4: ='Purchase Order & Landed Cost'!N4 -> 455.64 | G4: =E4*F4 -> 455640
A5: Mip002 | B5: Blood Tubing Set | C5: ='Purchase Order & Landed Cost'!O5 -> 4500 | D5: =SUMIF('Sales Tracking & Revenue'!E$4:E$10, A5, 'Sales Tracking & Revenue'!G$4:G$10) -> 3000 | E5: =C5-D5 -> 1500 | F5: ='Purchase Order & Landed Cost'!N5 -> 186.27 | G5: =E5*F5 -> 279405
A6: Mip003 | B6: A.V Fistula Needle | C6: ='Purchase Order & Landed Cost'!O6 -> 35000 | D6: =SUMIF('Sales Tracking & Revenue'!E$4:E$10, A6, 'Sales Tracking & Revenue'!G$4:G$10) -> 20000 | E6: =C6-D6 -> 15000 | F6: ='Purchase Order & Landed Cost'!N6 -> 36.74 | G6: =E6*F6 -> 551100
A7: Total Summary | C7: =SUM(C4:C6) -> 44000 | D7: =SUM(D4:D6) -> 26500 | E7: =SUM(E4:E6) -> 17500 | G7: =SUM(G4:G6) -> 1286145

Sheet Sales Tracking & Revenue
A1: SALES LEDGER & REVENUE REALIZATION
A3: Invoice No | B3: Sales Date | C3: Customer Name | D3: Product Name | E3: Product Code | F3: Unit Landed Cost (COGS) | G3: QTY Sold | H3: Unit Sale Price | I3: Total Cost Amount | J3: Total Gross Revenue | K3: Profit Margin / Unit | L3: Total Profit Realized
A4: INV-2026-001 | B4: 2026-06-25 | C4: Dhaka Medical College Hospital | D4: Dialyzer | E4: Mip001 | F4: =VLOOKUP(E4, 'Warehouse Inventory Management'!A$4:G$6, 6, FALSE) -> 455.64 | G4: 3000 | H4: 640 | I4: =F4*G4 -> 1366920 | J4: =H4*G4 -> 1920000 | K4: =H4-F4 -> 184.36 | L4: =J4-I4 -> 553080
A5: INV-2026-001 | B5: 2026-06-25 | C5: Dhaka Medical College Hospital | D5: Blood Tubing Set | E5: Mip002 | F5: =VLOOKUP(E5, 'Warehouse Inventory Management'!A$4:G$6, 6, FALSE) -> 186.27 | G5: 3000 | H5: 215 | I5: =F5*G5 -> 558810 | J5: =H5*G5 -> 645000 | K5: =H5-F5 -> 28.73 | L5: =J5-I5 -> 86190
A6: INV-2026-002 | B6: 2026-06-26 | C6: Popular Hospital Uttara | D6: Dialyzer | E6: Mip001 | F6: =VLOOKUP(E6, 'Warehouse Inventory Management'!A$4:G$6, 6, FALSE) -> 455.64 | G6: 500 | H6: 650 | I6: =F6*G6 -> 227820 | J6: =H6*G6 -> 325000 | K6: =H6-F6 -> 194.36 | L6: =J6-I6 -> 97180
A7: INV-2026-003 | B7: 2026-06-27 | C7: Labaid Group | D7: A.V Fistula Needle | E7: Mip003 | F7: =VLOOKUP(E7, 'Warehouse Inventory Management'!A$4:G$6, 6, FALSE) -> 36.74 | G7: 20000 | H7: 54 | I7: =F7*G7 -> 734800 | J7: =H7*G7 -> 1080000 | K7: =H7-F7 -> 17.26 | L7: =J7-I7 -> 345200
A8: Total Summary | G8: =SUM(G4:G7) -> 26500 | I8: =SUM(I4:I7) -> 2888350 | J8: =SUM(J4:J7) -> 3970000 | L8: =SUM(L4:L7) -> 1081650
